basefolder/__init__.py
basefolder/predictnow/__init__.py
basefolder/predictnow/find_files_with_specific_extensions.py
basefolder/predictnow/notifier.py
basefolder/predictnow/pdapi.py
basefolder/predictnow/predict_result.py
basefolder/predictnow/training_result.py
predictnow_api-2.0.0.dist-info/LICENSE.txt
predictnow_api-2.0.0.dist-info/METADATA
predictnow_api-2.0.0.dist-info/WHEEL
predictnow_api-2.0.0.dist-info/top_level.txt
predictnow_api-2.0.0.dist-info/RECORD
